cli_tool/__init__.py
cli_tool/click_demo.py
devops_cli_Nicole-0.1.4.dist-info/METADATA
devops_cli_Nicole-0.1.4.dist-info/WHEEL
devops_cli_Nicole-0.1.4.dist-info/entry_points.txt
devops_cli_Nicole-0.1.4.dist-info/top_level.txt
devops_cli_Nicole-0.1.4.dist-info/RECORD
