Metadata-Version: 2.1
Name: devops-cli-Nicole
Version: 0.1.4
Summary: DevOps Tool
Home-page: https://test.com
Author: Nicole
Author-email: nicolechow@live.cn
License: MIT
Platform: UNKNOWN
Classifier: Development Status :: 5 - Production/Stable
Classifier: Intended Audience :: Developers
Classifier: Operating System :: Unix
Classifier: Operating System :: POSIX
Classifier: Programming Language :: Python
Classifier: Programming Language :: Python :: 3.7
Classifier: Topic :: Utilities
Requires-Dist: click
Requires-Dist: requests
Requires-Dist: boto3
